cmd/__init__.py
cmd/code_gen.py
zarban_python_sdk-0.1.dist-info/LICENSE
zarban_python_sdk-0.1.dist-info/METADATA
zarban_python_sdk-0.1.dist-info/WHEEL
zarban_python_sdk-0.1.dist-info/entry_points.txt
zarban_python_sdk-0.1.dist-info/top_level.txt
zarban_python_sdk-0.1.dist-info/RECORD
