Metadata-Version: 2.1
Name: zarban-python-sdk
Version: 0.1
Summary: Python SDK for Zarban
Home-page: https://github.com/zarbanio/zarban-py
Author: Zarban
Author-email: info@zarban.io
Classifier: Programming Language :: Python :: 3
Classifier: License :: OSI Approved :: MIT License
Classifier: Operating System :: OS Independent
License-File: LICENSE
Requires-Dist: openapi-generator-cli
